.gitignore
.travis.yml
CHANGELOG.rst
LICENSE
MANIFEST.in
Makefile
README.rst
setup.cfg
setup.py
tox.ini
Mopidy_Jellyfin.egg-info/PKG-INFO
Mopidy_Jellyfin.egg-info/SOURCES.txt
Mopidy_Jellyfin.egg-info/dependency_links.txt
Mopidy_Jellyfin.egg-info/entry_points.txt
Mopidy_Jellyfin.egg-info/not-zip-safe
Mopidy_Jellyfin.egg-info/requires.txt
Mopidy_Jellyfin.egg-info/top_level.txt
mopidy_jellyfin/__init__.py
mopidy_jellyfin/backend.py
mopidy_jellyfin/ext.conf
mopidy_jellyfin/frontend.py
mopidy_jellyfin/http.py
mopidy_jellyfin/library.py
mopidy_jellyfin/playback.py
mopidy_jellyfin/playlists.py
mopidy_jellyfin/remote.py
mopidy_jellyfin/utils.py
mopidy_jellyfin/ws_client.py
tests/conftest.py
tests/test_backend.py
tests/test_extension.py
tests/test_library.py
tests/test_playback.py
tests/test_remote.py
tests/test_utils.py
tests/data/get_albums0.json
tests/data/get_artists0.json
tests/data/get_music_root0.json
tests/data/get_music_root1.json
tests/data/get_token0.json
tests/data/get_token1.json
tests/data/get_tracks0.json
tests/data/get_user0.json
tests/data/get_user1.json
tests/data/lookup_artist0.json
tests/data/search_album0.json
tests/data/search_artist0.json
tests/data/search_audio0.json
tests/data/track0.json
tests/data/track1.json
tests/data/track2.json