Metadata-Version: 2.2
Name: Mopidy-Jellyfin
Version: 1.0.6
Summary: Mopidy extension for playing music from jellyfin
Home-page: https://github.com/jellyfin/mopidy-jellyfin
Author: Matt Carlton
Author-email: mcarlton00@gmail.com
License: Apache License, Version 2.0
Classifier: Environment :: No Input/Output (Daemon)
Classifier: Intended Audience :: End Users/Desktop
Classifier: License :: OSI Approved :: Apache Software License
Classifier: Operating System :: OS Independent
Classifier: Programming Language :: Python :: 3
Classifier: Topic :: Multimedia :: Sound/Audio :: Players
License-File: LICENSE
Requires-Dist: setuptools
Requires-Dist: Mopidy>=2.0
Requires-Dist: Pykka>=1.1
Requires-Dist: requests>=2.20
Requires-Dist: unidecode>=1.1
Requires-Dist: websocket-client>=0.57
Dynamic: author
Dynamic: author-email
Dynamic: classifier
Dynamic: description
Dynamic: home-page
Dynamic: license
Dynamic: requires-dist
Dynamic: summary
